{"PERSON_ID":{"0":1628399},"FIRST_NAME":{"0":"Tyler"},"LAST_NAME":{"0":"Lydon"},"DISPLAY_FIRST_LAST":{"0":"Tyler Lydon"},"DISPLAY_LAST_COMMA_FIRST":{"0":"Lydon, Tyler"},"DISPLAY_FI_LAST":{"0":"T. Lydon"},"BIRTHDATE":{"0":"1996-04-09T00:00:00"},"SCHOOL":{"0":"Syracuse"},"COUNTRY":{"0":"USA"},"LAST_AFFILIATION":{"0":"Syracuse\/USA"},"HEIGHT":{"0":"6-10"},"WEIGHT":{"0":"225"},"SEASON_EXP":{"0":2},"JERSEY":{"0":"20"},"POSITION":{"0":"Forward"},"ROSTERSTATUS":{"0":"Active"},"TEAM_ID":{"0":1610612743},"TEAM_NAME":{"0":"Nuggets"},"TEAM_ABBREVIATION":{"0":"DEN"},"TEAM_CODE":{"0":"nuggets"},"TEAM_CITY":{"0":"Denver"},"PLAYERCODE":{"0":"tyler_lydon"},"FROM_YEAR":{"0":2017},"TO_YEAR":{"0":2019},"DLEAGUE_FLAG":{"0":"Y"},"NBA_FLAG":{"0":"Y"},"GAMES_PLAYED_FLAG":{"0":"Y"},"DRAFT_YEAR":{"0":"2017"},"DRAFT_ROUND":{"0":"1"},"DRAFT_NUMBER":{"0":"24"}}