{"PERSON_ID":{"0":1628993},"FIRST_NAME":{"0":"Alize"},"LAST_NAME":{"0":"Johnson"},"DISPLAY_FIRST_LAST":{"0":"Alize Johnson"},"DISPLAY_LAST_COMMA_FIRST":{"0":"Johnson, Alize"},"DISPLAY_FI_LAST":{"0":"A. Johnson"},"BIRTHDATE":{"0":"1996-04-22T00:00:00"},"SCHOOL":{"0":"Missouri State University"},"COUNTRY":{"0":"USA"},"LAST_AFFILIATION":{"0":"Missouri State University\/USA"},"HEIGHT":{"0":"6-9"},"WEIGHT":{"0":"212"},"SEASON_EXP":{"0":1},"JERSEY":{"0":"24"},"POSITION":{"0":"Forward"},"ROSTERSTATUS":{"0":"Active"},"TEAM_ID":{"0":1610612754},"TEAM_NAME":{"0":"Pacers"},"TEAM_ABBREVIATION":{"0":"IND"},"TEAM_CODE":{"0":"pacers"},"TEAM_CITY":{"0":"Indiana"},"PLAYERCODE":{"0":"alize_johnson"},"FROM_YEAR":{"0":2018},"TO_YEAR":{"0":2019},"DLEAGUE_FLAG":{"0":"Y"},"NBA_FLAG":{"0":"Y"},"GAMES_PLAYED_FLAG":{"0":"Y"},"DRAFT_YEAR":{"0":"2018"},"DRAFT_ROUND":{"0":"2"},"DRAFT_NUMBER":{"0":"50"}}