{"PERSON_ID":{"0":1628656},"FIRST_NAME":{"0":"Billy"},"LAST_NAME":{"0":"Garrett"},"DISPLAY_FIRST_LAST":{"0":"Billy Garrett"},"DISPLAY_LAST_COMMA_FIRST":{"0":"Garrett, Billy"},"DISPLAY_FI_LAST":{"0":"B. Garrett"},"BIRTHDATE":{"0":"1994-10-16T00:00:00"},"SCHOOL":{"0":"DePaul University"},"COUNTRY":{"0":"USA"},"LAST_AFFILIATION":{"0":"DePaul\/USA"},"HEIGHT":{"0":"6-6"},"WEIGHT":{"0":"215"},"SEASON_EXP":{"0":1},"JERSEY":{"0":"3"},"POSITION":{"0":"Guard-Forward"},"ROSTERSTATUS":{"0":"Active"},"TEAM_ID":{"0":1610612752},"TEAM_NAME":{"0":"Knicks"},"TEAM_ABBREVIATION":{"0":"NYK"},"TEAM_CODE":{"0":"knicks"},"TEAM_CITY":{"0":"New York"},"PLAYERCODE":{"0":"billy_garrett"},"FROM_YEAR":{"0":2018},"TO_YEAR":{"0":2019},"DLEAGUE_FLAG":{"0":"Y"},"NBA_FLAG":{"0":"Y"},"GAMES_PLAYED_FLAG":{"0":"Y"},"DRAFT_YEAR":{"0":"Undrafted"},"DRAFT_ROUND":{"0":"Undrafted"},"DRAFT_NUMBER":{"0":"Undrafted"}}