{"PERSON_ID":{"0":201967},"FIRST_NAME":{"0":"Dante"},"LAST_NAME":{"0":"Cunningham"},"DISPLAY_FIRST_LAST":{"0":"Dante Cunningham"},"DISPLAY_LAST_COMMA_FIRST":{"0":"Cunningham, Dante"},"DISPLAY_FI_LAST":{"0":"D. Cunningham"},"BIRTHDATE":{"0":"1987-04-22T00:00:00"},"SCHOOL":{"0":"Villanova"},"COUNTRY":{"0":"USA"},"LAST_AFFILIATION":{"0":"Villanova\/USA"},"HEIGHT":{"0":"6-8"},"WEIGHT":{"0":"230"},"SEASON_EXP":{"0":10},"JERSEY":{"0":"33"},"POSITION":{"0":"Forward"},"ROSTERSTATUS":{"0":"Active"},"TEAM_ID":{"0":1610612759},"TEAM_NAME":{"0":"Spurs"},"TEAM_ABBREVIATION":{"0":"SAS"},"TEAM_CODE":{"0":"spurs"},"TEAM_CITY":{"0":"San Antonio"},"PLAYERCODE":{"0":"dante_cunningham"},"FROM_YEAR":{"0":2009},"TO_YEAR":{"0":2019},"DLEAGUE_FLAG":{"0":"N"},"NBA_FLAG":{"0":"Y"},"GAMES_PLAYED_FLAG":{"0":"Y"},"DRAFT_YEAR":{"0":"2009"},"DRAFT_ROUND":{"0":"2"},"DRAFT_NUMBER":{"0":"33"}}