{"PERSON_ID":{"0":202687},"FIRST_NAME":{"0":"Bismack"},"LAST_NAME":{"0":"Biyombo"},"DISPLAY_FIRST_LAST":{"0":"Bismack Biyombo"},"DISPLAY_LAST_COMMA_FIRST":{"0":"Biyombo, Bismack"},"DISPLAY_FI_LAST":{"0":"B. Biyombo"},"BIRTHDATE":{"0":"1992-08-28T00:00:00"},"SCHOOL":{"0":" "},"COUNTRY":{"0":"Democratic Republic of the Congo"},"LAST_AFFILIATION":{"0":"Baloncesto Fuenlabrada\/Democratic Republic of Cong"},"HEIGHT":{"0":"6-9"},"WEIGHT":{"0":"255"},"SEASON_EXP":{"0":8},"JERSEY":{"0":"8"},"POSITION":{"0":"Center"},"ROSTERSTATUS":{"0":"Active"},"TEAM_ID":{"0":1610612766},"TEAM_NAME":{"0":"Hornets"},"TEAM_ABBREVIATION":{"0":"CHA"},"TEAM_CODE":{"0":"hornets"},"TEAM_CITY":{"0":"Charlotte"},"PLAYERCODE":{"0":"bismack_biyombo"},"FROM_YEAR":{"0":2011},"TO_YEAR":{"0":2019},"DLEAGUE_FLAG":{"0":"N"},"NBA_FLAG":{"0":"Y"},"GAMES_PLAYED_FLAG":{"0":"Y"},"DRAFT_YEAR":{"0":"2011"},"DRAFT_ROUND":{"0":"1"},"DRAFT_NUMBER":{"0":"7"}}