{"PLAYER_ID":{"0":1628462,"1":1629010,"2":201601,"3":1629116,"4":1627740,"5":1629037,"6":202397,"7":1629155},"FIRST_NAME":{"0":"Milos","1":"Jerome","2":"Luc","3":"Angel","4":"Henry","5":"Keenan","6":"Ish","7":"Zach"},"LAST_NAME":{"0":"Teodosic","1":"Robinson","2":"Mbah a Moute","3":"Delgado","4":"Ellenson","5":"Evans","6":"Smith","7":"Lofton"},"JERSEY_NUM":{"0":"4   ","1":"10  ","2":"12  ","3":"31  ","4":"8   ","5":"12  ","6":"14  ","7":"18  "},"TEAM_ID":{"0":1610612746,"1":1610612746,"2":1610612746,"3":1610612746,"4":1610612765,"5":1610612765,"6":1610612765,"7":1610612765},"TEAM_CITY":{"0":"LA","1":"LA","2":"LA","3":"LA","4":"Detroit","5":"Detroit","6":"Detroit","7":"Detroit"},"TEAM_NAME":{"0":"Clippers","1":"Clippers","2":"Clippers","3":"Clippers","4":"Pistons","5":"Pistons","6":"Pistons","7":"Pistons"},"TEAM_ABBREVIATION":{"0":"LAC","1":"LAC","2":"LAC","3":"LAC","4":"DET","5":"DET","6":"DET","7":"DET"}}