{"PLAYER_ID":{"0":1628505,"1":1628518,"2":1628515,"3":202389,"4":1627863,"5":1629053,"6":203991,"7":1628392},"FIRST_NAME":{"0":"Troy","1":"Amile","2":"Isaiah","3":"Timofey","4":"Danuel","5":"Vincent","6":"Clint","7":"Isaiah"},"LAST_NAME":{"0":"Caupain","1":"Jefferson","2":"Briscoe","3":"Mozgov","4":"House Jr.","5":"Edwards","6":"Capela","7":"Hartenstein"},"JERSEY_NUM":{"0":"3   ","1":"11  ","2":"13  ","3":"21  ","4":"4   ","5":"12  ","6":"15  ","7":"55  "},"TEAM_ID":{"0":1610612753,"1":1610612753,"2":1610612753,"3":1610612753,"4":1610612745,"5":1610612745,"6":1610612745,"7":1610612745},"TEAM_CITY":{"0":"Orlando","1":"Orlando","2":"Orlando","3":"Orlando","4":"Houston","5":"Houston","6":"Houston","7":"Houston"},"TEAM_NAME":{"0":"Magic","1":"Magic","2":"Magic","3":"Magic","4":"Rockets","5":"Rockets","6":"Rockets","7":"Rockets"},"TEAM_ABBREVIATION":{"0":"ORL","1":"ORL","2":"ORL","3":"ORL","4":"HOU","5":"HOU","6":"HOU","7":"HOU"}}