{"PLAYER_ID":{"0":1628396,"1":203526,"2":1628513,"3":1628463,"4":202326,"5":2738,"6":1629094},"FIRST_NAME":{"0":"Tony","1":"Raul","2":"Naz","3":"Tyler","4":"DeMarcus","5":"Andre","6":"Marcus"},"LAST_NAME":{"0":"Bradley","1":"Neto","2":"Mitrou-Long","3":"Cavanaugh","4":"Cousins","5":"Iguodala","6":"Derrickson"},"JERSEY_NUM":{"0":"13  ","1":"25  ","2":"30  ","3":"34  ","4":"0   ","5":"9   ","6":"32  "},"TEAM_ID":{"0":1610612762,"1":1610612762,"2":1610612762,"3":1610612762,"4":1610612744,"5":1610612744,"6":1610612744},"TEAM_CITY":{"0":"Utah","1":"Utah","2":"Utah","3":"Utah","4":"Golden State","5":"Golden State","6":"Golden State"},"TEAM_NAME":{"0":"Jazz","1":"Jazz","2":"Jazz","3":"Jazz","4":"Warriors","5":"Warriors","6":"Warriors"},"TEAM_ABBREVIATION":{"0":"UTA","1":"UTA","2":"UTA","3":"UTA","4":"GSW","5":"GSW","6":"GSW"}}