{"PLAYER_ID":{"0":1629167,"1":201601,"2":1628405,"3":1629116,"4":202340,"5":203937,"6":101139,"7":1628991,"8":1628415,"9":201149},"FIRST_NAME":{"0":"Justin","1":"Luc","2":"Johnathan","3":"Angel","4":"Avery","5":"Kyle","6":"CJ","7":"Jaren","8":"Dillon","9":"Joakim"},"LAST_NAME":{"0":"Bibbs","1":"Mbah a Moute","2":"Motley","3":"Delgado","4":"Bradley","5":"Anderson","6":"Miles","7":"Jackson Jr.","8":"Brooks","9":"Noah"},"JERSEY_NUM":{"0":"11  ","1":"12  ","2":"15  ","3":"31  ","4":"0   ","5":"1   ","6":"6   ","7":"13  ","8":"24  ","9":"55  "},"TEAM_ID":{"0":1610612746,"1":1610612746,"2":1610612746,"3":1610612746,"4":1610612763,"5":1610612763,"6":1610612763,"7":1610612763,"8":1610612763,"9":1610612763},"TEAM_CITY":{"0":"LA","1":"LA","2":"LA","3":"LA","4":"Memphis","5":"Memphis","6":"Memphis","7":"Memphis","8":"Memphis","9":"Memphis"},"TEAM_NAME":{"0":"Clippers","1":"Clippers","2":"Clippers","3":"Clippers","4":"Grizzlies","5":"Grizzlies","6":"Grizzlies","7":"Grizzlies","8":"Grizzlies","9":"Grizzlies"},"TEAM_ABBREVIATION":{"0":"LAC","1":"LAC","2":"LAC","3":"LAC","4":"MEM","5":"MEM","6":"MEM","7":"MEM","8":"MEM","9":"MEM"}}