{"PLAYER_ID":{"0":2546,"1":1628990,"2":1628976,"3":1627756,"4":1628999,"5":1627884,"6":201609,"7":1629130},"FIRST_NAME":{"0":"Carmelo","1":"Chandler","2":"Wendell","3":"Denzel","4":"Yante","5":"Derrick","6":"Goran","7":"Duncan"},"LAST_NAME":{"0":"Anthony","1":"Hutchison","2":"Carter Jr.","3":"Valentine","4":"Maten","5":"Jones Jr.","6":"Dragic","7":"Robinson"},"JERSEY_NUM":{"0":"7   ","1":"15  ","2":"34  ","3":"45  ","4":"00  ","5":"5   ","6":"7   ","7":"55  "},"TEAM_ID":{"0":1610612741,"1":1610612741,"2":1610612741,"3":1610612741,"4":1610612748,"5":1610612748,"6":1610612748,"7":1610612748},"TEAM_CITY":{"0":"Chicago","1":"Chicago","2":"Chicago","3":"Chicago","4":"Miami","5":"Miami","6":"Miami","7":"Miami"},"TEAM_NAME":{"0":"Bulls","1":"Bulls","2":"Bulls","3":"Bulls","4":"Heat","5":"Heat","6":"Heat","7":"Heat"},"TEAM_ABBREVIATION":{"0":"CHI","1":"CHI","2":"CHI","3":"CHI","4":"MIA","5":"MIA","6":"MIA","7":"MIA"}}