{"PLAYER_ID":{"0":202687,"1":1629147,"2":1629122,"3":1627740,"4":1629037,"5":202397,"6":1629155,"7":203922},"FIRST_NAME":{"0":"Bismack","1":"Joe","2":"J.P.","3":"Henry","4":"Keenan","5":"Ish","6":"Zach","7":"Glenn"},"LAST_NAME":{"0":"Biyombo","1":"Chealey","2":"Macura","3":"Ellenson","4":"Evans","5":"Smith","6":"Lofton","7":"Robinson III"},"JERSEY_NUM":{"0":"8   ","1":"31  ","2":"55  ","3":"8   ","4":"12  ","5":"14  ","6":"18  ","7":"22  "},"TEAM_ID":{"0":1610612766,"1":1610612766,"2":1610612766,"3":1610612765,"4":1610612765,"5":1610612765,"6":1610612765,"7":1610612765},"TEAM_CITY":{"0":"Charlotte","1":"Charlotte","2":"Charlotte","3":"Detroit","4":"Detroit","5":"Detroit","6":"Detroit","7":"Detroit"},"TEAM_NAME":{"0":"Hornets","1":"Hornets","2":"Hornets","3":"Pistons","4":"Pistons","5":"Pistons","6":"Pistons","7":"Pistons"},"TEAM_ABBREVIATION":{"0":"CHA","1":"CHA","2":"CHA","3":"DET","4":"DET","5":"DET","6":"DET","7":"DET"}}