{"PLAYER_ID":{"0":1628366,"1":1628404,"2":202362,"3":1627742,"4":2544,"5":1629018,"6":203994},"FIRST_NAME":{"0":"Lonzo","1":"Josh","2":"Lance","3":"Brandon","4":"LeBron","5":"Gary","6":"Jusuf"},"LAST_NAME":{"0":"Ball","1":"Hart","2":"Stephenson","3":"Ingram","4":"James","5":"Trent Jr.","6":"Nurkic"},"JERSEY_NUM":{"0":"2   ","1":"3   ","2":"6   ","3":"14  ","4":"23  ","5":"9   ","6":"27  "},"TEAM_ID":{"0":1610612747,"1":1610612747,"2":1610612747,"3":1610612747,"4":1610612747,"5":1610612757,"6":1610612757},"TEAM_CITY":{"0":"Los Angeles","1":"Los Angeles","2":"Los Angeles","3":"Los Angeles","4":"Los Angeles","5":"Portland","6":"Portland"},"TEAM_NAME":{"0":"Lakers","1":"Lakers","2":"Lakers","3":"Lakers","4":"Lakers","5":"Trail Blazers","6":"Trail Blazers"},"TEAM_ABBREVIATION":{"0":"LAL","1":"LAL","2":"LAL","3":"LAL","4":"LAL","5":"POR","6":"POR"}}