{"PLAYER_ID":{"0":202340,"1":201601,"2":1628405,"3":1629116,"4":201952,"5":1629123,"6":1628383},"FIRST_NAME":{"0":"Avery","1":"Luc","2":"Johnathan","3":"Angel","4":"Jeff","5":"Jared","6":"Justin"},"LAST_NAME":{"0":"Bradley","1":"Mbah a Moute","2":"Motley","3":"Delgado","4":"Teague","5":"Terrell","6":"Patton"},"JERSEY_NUM":{"0":"11  ","1":"12  ","2":"15  ","3":"31  ","4":"0   ","5":"3   ","6":"24  "},"TEAM_ID":{"0":1610612746,"1":1610612746,"2":1610612746,"3":1610612746,"4":1610612750,"5":1610612750,"6":1610612750},"TEAM_CITY":{"0":"LA","1":"LA","2":"LA","3":"LA","4":"Minnesota","5":"Minnesota","6":"Minnesota"},"TEAM_NAME":{"0":"Clippers","1":"Clippers","2":"Clippers","3":"Clippers","4":"Timberwolves","5":"Timberwolves","6":"Timberwolves"},"TEAM_ABBREVIATION":{"0":"LAC","1":"LAC","2":"LAC","3":"LAC","4":"MIN","5":"MIN","6":"MIN"}}