{"PLAYER_ID":{"0":1629037,"1":1628379,"2":1627740,"3":1629155,"4":101139,"5":1628070,"6":201586,"7":1626181,"8":1628449},"FIRST_NAME":{"0":"Keenan","1":"Luke","2":"Henry","3":"Zach","4":"CJ","5":"Jordan","6":"Serge","7":"Norman","8":"Chris"},"LAST_NAME":{"0":"Evans","1":"Kennard","2":"Ellenson","3":"Lofton","4":"Miles","5":"Loyd","6":"Ibaka","7":"Powell","8":"Boucher"},"JERSEY_NUM":{"0":"12  ","1":"5   ","2":"8   ","3":"18  ","4":"0   ","5":"8   ","6":"9   ","7":"24  ","8":"25  "},"TEAM_ID":{"0":1610612765,"1":1610612765,"2":1610612765,"3":1610612765,"4":1610612761,"5":1610612761,"6":1610612761,"7":1610612761,"8":1610612761},"TEAM_CITY":{"0":"Detroit","1":"Detroit","2":"Detroit","3":"Detroit","4":"Toronto","5":"Toronto","6":"Toronto","7":"Toronto","8":"Toronto"},"TEAM_NAME":{"0":"Pistons","1":"Pistons","2":"Pistons","3":"Pistons","4":"Raptors","5":"Raptors","6":"Raptors","7":"Raptors","8":"Raptors"},"TEAM_ABBREVIATION":{"0":"DET","1":"DET","2":"DET","3":"DET","4":"TOR","5":"TOR","6":"TOR","7":"TOR","8":"TOR"}}