{"GAME_DATE_EST":{"0":"2019-01-13T00:00:00","1":"2019-01-13T00:00:00"},"GAME_SEQUENCE":{"0":2,"1":2},"GAME_ID":{"0":"0021800639","1":"0021800639"},"TEAM_ID":{"0":1610612764,"1":1610612761},"TEAM_ABBREVIATION":{"0":"WAS","1":"TOR"},"TEAM_CITY_NAME":{"0":"Washington","1":"Toronto"},"TEAM_NICKNAME":{"0":"Wizards","1":"Raptors"},"TEAM_WINS_LOSSES":{"0":"18-26","1":"33-12"},"PTS_QTR1":{"0":21,"1":36},"PTS_QTR2":{"0":29,"1":25},"PTS_QTR3":{"0":34,"1":37},"PTS_QTR4":{"0":40,"1":26},"PTS_OT1":{"0":7,"1":7},"PTS_OT2":{"0":7,"1":9},"PTS_OT3":{"0":0,"1":0},"PTS_OT4":{"0":0,"1":0},"PTS_OT5":{"0":0,"1":0},"PTS_OT6":{"0":0,"1":0},"PTS_OT7":{"0":0,"1":0},"PTS_OT8":{"0":0,"1":0},"PTS_OT9":{"0":0,"1":0},"PTS_OT10":{"0":0,"1":0},"PTS":{"0":138,"1":140}}