{"SEASON_ID":{"0":"22018","1":"22018","2":"22018"},"Player_ID":{"0":202700,"1":202700,"2":202700},"Game_ID":{"0":"0021801227","1":"0021801196","2":"0021801182"},"GAME_DATE":{"0":"APR 10, 2019","1":"APR 07, 2019","2":"APR 05, 2019"},"MATCHUP":{"0":"SAS vs. DAL","1":"SAS @ CLE","2":"SAS @ WAS"},"WL":{"0":"W","1":"W","2":"W"},"MIN":{"0":3,"1":6,"2":4},"FGM":{"0":1,"1":1,"2":1},"FGA":{"0":1,"1":1,"2":4},"FG_PCT":{"0":1.0,"1":1.0,"2":0.25},"FG3M":{"0":0,"1":0,"2":0},"FG3A":{"0":0,"1":0,"2":0},"FG3_PCT":{"0":0.0,"1":0.0,"2":0.0},"FTM":{"0":0,"1":0,"2":0},"FTA":{"0":0,"1":2,"2":0},"FT_PCT":{"0":0.0,"1":0.0,"2":0.0},"OREB":{"0":1,"1":0,"2":1},"DREB":{"0":0,"1":1,"2":0},"REB":{"0":1,"1":1,"2":1},"AST":{"0":0,"1":1,"2":0},"STL":{"0":0,"1":0,"2":0},"BLK":{"0":0,"1":0,"2":1},"TOV":{"0":2,"1":0,"2":1},"PF":{"0":1,"1":4,"2":1},"PTS":{"0":2,"1":2,"2":2},"PLUS_MINUS":{"0":-6,"1":-4,"2":-6},"VIDEO_AVAILABLE":{"0":1,"1":1,"2":1}}